src/main/python/__init__.py
sparkbasics-1.0.0.dist-info/METADATA
sparkbasics-1.0.0.dist-info/WHEEL
sparkbasics-1.0.0.dist-info/top_level.txt
sparkbasics-1.0.0.dist-info/RECORD
