Metadata-Version: 2.1
Name: sparkbasics
Version: 1.0.0
Summary: BDCC Pyspark Basics project
